MANIFEST.in
setup.py
banta/__init__.py
banta/changelog.txt
banta/fix.py
banta/gpl-3.0.txt
banta/rc.py
banta/user.qss
banta/utils.py
banta.egg-info/PKG-INFO
banta.egg-info/SOURCES.txt
banta.egg-info/dependency_links.txt
banta.egg-info/entry_points.txt
banta.egg-info/requires.txt
banta.egg-info/top_level.txt
banta/db/__init__.py
banta/db/cnx.py
banta/db/config.py
banta/db/models.py
banta/db/old_updates.py
banta/db/updates.py
banta/packages/__init__.py
banta/packages/barbarella/__init__.py
banta/packages/barbarella/db_updates.py
banta/packages/base/__init__.py
banta/packages/base/bills.py
banta/packages/base/clients.py
banta/packages/base/csv_imports.py
banta/packages/base/feeds.py
banta/packages/base/products.py
banta/packages/base/providers.py
banta/packages/base/tbill.py
banta/packages/base/tpay.py
banta/packages/base/users.py
banta/packages/experimental/__init__.py
banta/packages/experimental/allopass.py
banta/packages/experimental/qmlsame.py
banta/packages/optional/__init__.py
banta/packages/optional/bill_list.py
banta/packages/optional/buys.py
banta/packages/optional/categories.py
banta/packages/optional/client_details.py
banta/packages/optional/limits.py
banta/packages/optional/reports.py
banta/packages/optional/type_tax.py
banta/packages/optional/webservice.py
banta/packages/optional/printer/__init__.py
banta/packages/optional/printer/com_hasar.py
banta/packages/optional/printer/epsonFiscal.py
banta/packages/optional/printer/epsonFiscalDriver.py
banta/packages/optional/printer/epsonPrinter.py
banta/packages/optional/printer/fiscalGeneric.py
banta/packages/optional/printer/hasarPrinter.py
banta/packages/optional/printer/test.py
banta/test/__init__.py
banta/test/test_main.py
hooks/__init__.py
hooks/hook-zope.event.py
hooks/hook-zope.py