Metadata-Version: 1.1
Name: banta
Version: 1.23.0
Summary: Accounting, point of sale, inventory
Home-page: http://moongate.com.ar
Author: MoonGate
Author-email: mail@moongate.com.ar
License: GNU LGPL
Keywords: point-of-sale inventory accounting inventario stock control ventas billing facturacion
Platform: Platform Independent
Classifier: Operating System :: OS Independent
Classifier: License :: OSI Approved
Classifier: License :: OSI Approved :: GNU General Public License v3 (GPLv3)
Classifier: Programming Language :: Python
Classifier: Programming Language :: Python :: 2
Classifier: Natural Language :: Spanish
Classifier: Natural Language :: English
Classifier: Development Status :: 5 - Production/Stable
Classifier: Intended Audience :: Financial and Insurance Industry
Classifier: Intended Audience :: Developers
Classifier: Intended Audience :: End Users/Desktop
Classifier: Topic :: Office/Business
Classifier: Environment :: Win32 (MS Windows)
Classifier: Environment :: X11 Applications
Classifier: Environment :: MacOS X
Provides: banta
